zpassistant/__init__.py
zpassistant/ssologin.py
zpassistant-1.1.19.dist-info/LICENSE.txt
zpassistant-1.1.19.dist-info/METADATA
zpassistant-1.1.19.dist-info/WHEEL
zpassistant-1.1.19.dist-info/top_level.txt
zpassistant-1.1.19.dist-info/RECORD
