Metadata-Version: 2.1
Name: zpassistant
Version: 1.1.19
Summary: 公司内部使用单点登录
Home-page: https://gitee.com/naozeizei
Author: zhitao.mao
Author-email: mzt12450@163.com
Classifier: Programming Language :: Python :: 3
Classifier: License :: OSI Approved :: MIT License
Classifier: Operating System :: OS Independent
Requires-Python: >=3.6
License-File: LICENSE.txt
Requires-Dist: selenium
